{
"type": "FeatureCollection",
"name": "tunisia_charging_stations",
"crs": { "type": "name", "properties": { "name": "urn:ogc:def:crs:OGC:1.3:CRS84" } },
"features": [
{ "type": "Feature", "properties": { "osm_type": "node", "osm_id": 12449852375, "kind": "charging_station", "name": "Charging Station Total Kortoba", "brand": null, "operator": "TotalEnergies", "addr_full": null, "addr_street": null, "addr_city": null, "addr_postcode": null, "opening_hours": null, "phone": null, "website": null, "lat": 34.8391928, "lon": 10.7647117, "socket:schuko": null, "socket:type2": null, "socket:type2:output": null, "socket:ccs": null, "socket:ccs2": null, "socket:chademo": null, "capacity": null, "capacity:charging_points": null, "power": null, "maxcurrent": null, "voltage": null, "authentication": null, "operator:wikidata": "Q154037", "network": null, "fee": null, "payment:credit_cards": null, "authentication:app": null, "authentication:membership_card": null, "charge:output": null }, "geometry": { "type": "Point", "coordinates": [ 10.7647117, 34.8391928 ] } },
{ "type": "Feature", "properties": { "osm_type": "way", "osm_id": 1159157858, "kind": "charging_station", "name": "shell sidi hassine 2$", "brand": null, "operator": "Shell", "addr_full": null, "addr_street": null, "addr_city": null, "addr_postcode": null, "opening_hours": null, "phone": null, "website": null, "lat": 36.7643006, "lon": 10.1192249, "socket:schuko": null, "socket:type2": null, "socket:type2:output": null, "socket:ccs": null, "socket:ccs2": null, "socket:chademo": null, "capacity": null, "capacity:charging_points": null, "power": null, "maxcurrent": null, "voltage": null, "authentication": null, "operator:wikidata": "Q110716465", "network": null, "fee": null, "payment:credit_cards": null, "authentication:app": null, "authentication:membership_card": null, "charge:output": null }, "geometry": { "type": "Point", "coordinates": [ 10.1192249, 36.7643006 ] } },
{ "type": "Feature", "properties": { "osm_type": "node", "osm_id": 4510850190, "kind": "charging_station", "name": null, "brand": null, "operator": null, "addr_full": null, "addr_street": null, "addr_city": null, "addr_postcode": null, "opening_hours": null, "phone": null, "website": null, "lat": 36.7807266, "lon": 10.1937043, "socket:schuko": null, "socket:type2": null, "socket:type2:output": null, "socket:ccs": null, "socket:ccs2": null, "socket:chademo": null, "capacity": null, "capacity:charging_points": null, "power": null, "maxcurrent": null, "voltage": null, "authentication": null, "operator:wikidata": null, "network": null, "fee": null, "payment:credit_cards": null, "authentication:app": null, "authentication:membership_card": null, "charge:output": null }, "geometry": { "type": "Point", "coordinates": [ 10.1937043, 36.7807266 ] } }
]
}
